redis_rs-0.14.0.dist-info/METADATA
redis_rs-0.14.0.dist-info/WHEEL
redis_rs-0.14.0.dist-info/licenses/LICENSE
redis_rs/__init__.py
redis_rs/py.typed
redis_rs/client_async.pyi
redis_rs/__init__.pyi
redis_rs/client_async.py
redis_rs/types.py
redis_rs/exceptions/__init__.py
redis_rs/redis_rs.cpython-38-aarch64-linux-gnu.so
redis_rs-0.14.0.dist-info/RECORD
