Metadata-Version: 2.4
Name: redis-rs
Version: 0.14.0
Classifier: License :: OSI Approved :: MIT License
Classifier: Programming Language :: Rust
Classifier: Programming Language :: Python :: Implementation :: CPython
Classifier: Programming Language :: Python :: Implementation :: PyPy
Classifier: Framework :: AsyncIO
Classifier: Programming Language :: Python :: 3
Classifier: Programming Language :: Python :: 3 :: Only
Classifier: Programming Language :: Python :: 3.8
Classifier: Programming Language :: Python :: 3.9
Classifier: Programming Language :: Python :: 3.10
Classifier: Programming Language :: Python :: 3.11
Classifier: Programming Language :: Python :: 3.12
Classifier: Programming Language :: Python :: 3.13
License-File: LICENSE
Summary: Python wrapper for redis-rs
Keywords: redis,redis-cluster,rust
Author-email: Alexander Malev <yttrium@somedev.ru>
Requires-Python: >=3.8
Project-URL: Source Code, https://github.com/aamalev/redis-rs-py
Project-URL: Issues, https://github.com/aamalev/redis-rs-py/issues
Project-URL: Documentation, https://github.com/aamalev/redis-rs-py#using
Project-URL: Changelog, https://github.com/aamalev/redis-rs-py/releases
